numyra_gateway/__init__.py
numyra_gateway/proxy/__init__.py
numyra_gateway/proxy/addon_anthropic_sse.py
numyra_gateway/proxy/addon_anthropic_view.py
numyra_gateway/proxy/addon_list.py
numyra_gateway/proxy/annotate.py
numyra_gateway/proxy/sse_interceptor.py
numyra_gateway/proxy/start_gateway.py
numyra_gateway/proxy/traffic_view.py
numyra_gateway/streaming/__init__.py
numyra_gateway/streaming/anthropic_streaming.py
numyra_gateway/streaming/sse_parser.py
numyra_gateway-0.1.1.dist-info/WHEEL
numyra_gateway-0.1.1.dist-info/entry_points.txt
numyra_gateway-0.1.1.dist-info/METADATA
numyra_gateway-0.1.1.dist-info/RECORD
