Metadata-Version: 2.3
Name: numyra-gateway
Version: 0.1.1
Summary: Numyra Gateway
Keywords: anthropic,claude,proxy,streaming,sse,mitmproxy
Author: simone
Author-email: simone <simone.giacomelli@gmail.com>
License: Proprietary
Classifier: Development Status :: 3 - Alpha
Classifier: Intended Audience :: Developers
Classifier: License :: Other/Proprietary License
Classifier: Programming Language :: Python :: 3
Classifier: Programming Language :: Python :: 3.13
Classifier: Topic :: Internet :: Proxy Servers
Classifier: Topic :: Software Development :: Libraries :: Python Modules
Requires-Dist: mitmproxy>=12.1.2
Requires-Python: >=3.13
Project-URL: Homepage, https://numyra.io
